sjfmt_vendor/black.py
sjfmt_vendor/blackd.py
straitjacket/__init__.py
straitjacket/__main__.py
straitjacket/sjfmt.py
straitjacket/sjfmtd.py
straitjacket-202206.1026.dist-info/LICENSE
straitjacket-202206.1026.dist-info/METADATA
straitjacket-202206.1026.dist-info/WHEEL
straitjacket-202206.1026.dist-info/entry_points.txt
straitjacket-202206.1026.dist-info/top_level.txt
straitjacket-202206.1026.dist-info/zip-safe
straitjacket-202206.1026.dist-info/RECORD
