Metadata-Version: 2.1
Name: straitjacket
Version: 202206.1026
Summary: The Aligning Code Formatter for Python.
Home-page: https://github.com/mbarkhau/straitjacket
Author: Manuel Barkhau
Author-email: mbarkhau@gmail.com
License: MIT
Keywords: formatter yapf black pyfmt align
Platform: UNKNOWN
Classifier: Development Status :: 4 - Beta
Classifier: Environment :: Console
Classifier: Environment :: Other Environment
Classifier: Intended Audience :: Developers
Classifier: License :: OSI Approved :: MIT License
Classifier: Operating System :: Unix
Classifier: Operating System :: POSIX
Classifier: Operating System :: Microsoft :: Windows
Classifier: Operating System :: MacOS :: MacOS X
Classifier: Programming Language :: Python
Classifier: Programming Language :: Python :: 3
Classifier: Programming Language :: Python :: Implementation :: CPython
Classifier: Programming Language :: Python :: Implementation :: PyPy
Classifier: Topic :: Software Development :: Libraries
Classifier: Topic :: Software Development :: Libraries :: Python Modules
Requires-Python: >=3.6
Requires-Dist: black (==21.12b0)
Requires-Dist: regex (>=2020.1.8)
Requires-Dist: typing-extensions (>=3.10.0.0)
Requires-Dist: mypy-extensions (>=0.4.3)
Requires-Dist: dataclasses (>=0.6) ; python_version < "3.7"
Provides-Extra: d
Requires-Dist: black[d] (==21.12b0) ; extra == 'd'
